README.rst
setup.cfg
setup.py
pydocker_tools.egg-info/PKG-INFO
pydocker_tools.egg-info/SOURCES.txt
pydocker_tools.egg-info/dependency_links.txt
pydocker_tools.egg-info/entry_points.txt
pydocker_tools.egg-info/top_level.txt
pydockertools/__init__.py
pydockertools/jpydtools.py