Metadata-Version: 1.1
Name: pydocker-tools
Version: 0.0.1
Summary: pydocker-tools is a set of tools to work around lengthy or piped command line tools for docker
Home-page: https://github.com/jojees/pydocker-tools
Author: Joji Vithayathil Johny
Author-email: joji@jojees.net
License: MIT
Keywords: additional docker commandline tools
Platform: UNKNOWN
Classifier: Development Status :: 3 - Alpha
Classifier: Environment :: Console
Classifier: Intended Audience :: System Administrators
Classifier: Intended Audience :: Developers
Classifier: Intended Audience :: End Users/Desktop
Classifier: Intended Audience :: Information Technology
Classifier: Intended Audience :: Science/Research
Classifier: License :: OSI Approved :: MIT License
Classifier: Operating System :: Unix
Classifier: Operating System :: POSIX :: Linux
Classifier: Programming Language :: Python :: 2.7
Classifier: Topic :: Internet :: WWW/HTTP :: Dynamic Content :: CGI Tools/Libraries
Classifier: Topic :: Software Development :: Libraries :: Python Modules
Classifier: Topic :: System :: Shells
Classifier: Topic :: System :: Systems Administration
Classifier: Topic :: Text Processing :: Indexing
Classifier: Topic :: Utilities
